[
  {
    "_id": "5c9e17581b2804c21c89g7",
    "name": "Fish Tacos Ultimo ",
    "desc": "t is a long established fact that a reader will be distracted by the readable content of a page when looking at its layout. The point of using Lorem Ipsum is that it has a more-or-less normal distribution of letters, as opposed to using 'Content here, content here', making it look like readable English. Many desktop publishing packages and web page editors now use Lorem Ipsum as their d",
    "ingredients": [
      {
        "id": "xmbaa2pgi95fdxw3rqwy",
        "name": "item1",
        "qty": "2 units"
      },
      {
        "id": "xmbaa2fst95fdxw3rqwy",
        "name": "item2",
        "qty": "2 units"
      },
      {
        "id": "xmbaa2pgi95fdxw4rqwy",
        "name": "item3",
        "qty": "2 units"
      },
      {
        "id": "xmbaa2pgi95fdxw1rqwy",
        "name": "item4",
        "qty": "2 units"
      },
      {
        "id": "xmbaa9pgi95fdxw3rqwy",
        "name": "item5",
        "qty": "2 units"
      }
    ]
  },
  {
    "_id": "5c9e175817493f1361a225",
    "name": "Meatballs Divine",
    "desc": "Some quick example text to build on the card title and make up the bulk of the card's content.",
    "ingredients": []
  },
  {
    "_id": "5c9e17581b2804c21c89f7",
    "name": "Garlic Chicken ",
    "desc": "msalim",
    "ingredients": []
  },
  {
    "_id": "5c9e175817493f1361a226",
    "name": "To Die For Fettuccine Alfredo",
    "desc": "Some quick example text to build on the card title and make up the bulk of the card's content.",
    "ingredients": []
  },
  {
    "_id": "5c9e175817493f1361a22t",
    "name": "To Die For Fettuccine Alfredo",
    "desc": "Some quick example text to build on the card title and make up the bulk of the card's content.",
    "ingredients": [
      {
        "id": "xabaa2pgi95fdxw3rqwy",
        "name": "item1",
        "qty": "2 units"
      },
      {
        "id": "xbbaa2pgi95fdxw3rqwy",
        "name": "item2",
        "qty": "2 units"
      },
      {
        "id": "xcbaa2pgi95fdxw3rqwy",
        "name": "item5",
        "qty": "2 units"
      }
    ]
  }
]
